nonebot_plugin_mcqq_server/__init__.py
nonebot_plugin_mcqq_server/__main__.py
nonebot_plugin_mcqq_server/config.py
nonebot_plugin_mcqq_server/utils.py
nonebot_plugin_mcqq_server-1.1.4.dist-info/LICENSE
nonebot_plugin_mcqq_server-1.1.4.dist-info/METADATA
nonebot_plugin_mcqq_server-1.1.4.dist-info/WHEEL
nonebot_plugin_mcqq_server-1.1.4.dist-info/RECORD
