Metadata-Version: 2.3
Name: nonebot-plugin-mcqq-server
Version: 1.1.4
Summary: 采用本地读取 log 信息的方法的 Minecraft Server 消息互通插件。
Author: KarisAya
Author-email: karisaya@foxmail.com
Requires-Python: >=3.10,<4.0
Classifier: Programming Language :: Python :: 3
Classifier: Programming Language :: Python :: 3.10
Classifier: Programming Language :: Python :: 3.11
Classifier: Programming Language :: Python :: 3.12
Classifier: Programming Language :: Python :: 3.13
Requires-Dist: mcrcon (>=0.7.0,<0.8.0)
Requires-Dist: nonebot-plugin-alconna (>=0.59.0,<1.0.0)
Requires-Dist: nonebot-plugin-uninfo (>=0.8.2,<1.0.0)
Requires-Dist: nonebot2 (>=2.4.2,<3.0.0)
Requires-Dist: pydantic (>=2.11.7,<3.0.0)
